LICENSE
README.md
setup.py
smartdjango/__init__.py
smartdjango/analyse.py
smartdjango/choice.py
smartdjango/code.py
smartdjango/error.py
smartdjango/middleware.py
smartdjango/paginator.py
smartdjango.egg-info/PKG-INFO
smartdjango.egg-info/SOURCES.txt
smartdjango.egg-info/dependency_links.txt
smartdjango.egg-info/requires.txt
smartdjango.egg-info/top_level.txt
smartdjango/models/__init__.py
smartdjango/models/manager.py
smartdjango/models/queryset.py
smartdjango/utils/__init__.py
smartdjango/utils/inspect.py
smartdjango/utils/io.py
smartdjango/validation/__init__.py
smartdjango/validation/dict_validator.py
smartdjango/validation/key.py
smartdjango/validation/list_validator.py
smartdjango/validation/params.py
smartdjango/validation/validator.py