Metadata-Version: 2.1
Name: smartdjango
Version: 4.3.0
Summary: fast Django app development
Home-page: https://github.com/Jyonn/SmartDjango
Author: Jyonn Liu
Author-email: i@6-79.cn
License: MIT Licence
Keywords: django
Platform: any
License-File: LICENSE
Requires-Dist: smartify>=0.0.2
Requires-Dist: oba
